botlogger/__init__.py
botlogger/logger.py
botlogger/middlewares.py
botlogger/services.py
botlogger-0.0.8.dist-info/METADATA
botlogger-0.0.8.dist-info/WHEEL
botlogger-0.0.8.dist-info/top_level.txt
botlogger-0.0.8.dist-info/RECORD
