Metadata-Version: 2.1
Name: botlogger
Version: 0.0.8
Summary: Library to log messages from telegram bots
Author: justacold
Requires-Dist: loguru
Requires-Dist: aiohttp
